startrace/__init__.py
startrace/star_trace.py
startrace-2.0.4.dist-info/licenses/LICENSE
startrace-2.0.4.dist-info/METADATA
startrace-2.0.4.dist-info/WHEEL
startrace-2.0.4.dist-info/top_level.txt
startrace-2.0.4.dist-info/RECORD
