Metadata-Version: 2.4
Name: startrace
Version: 2.0.4
Summary: A lightweight string pattern tool
Author-email: William Coker <wdc23a@acu.edu>
License: GNU GENERAL PUBLIC LICENSE
Requires-Python: >=3.10
License-File: LICENSE
Dynamic: license-file
